endplay/__init__.py
endplay/config.py
endplay/dds/__init__.py
endplay/dds/analyse.py
endplay/dds/ddtable.py
endplay/dds/parscore.py
endplay/dds/solve.py
endplay/dealer/__init__.py
endplay/dealer/__main__.py
endplay/dealer/actions/__init__.py
endplay/dealer/actions/base.py
endplay/dealer/actions/html.py
endplay/dealer/actions/latex.py
endplay/dealer/actions/pdf.py
endplay/dealer/actions/terminal.py
endplay/dealer/constraint.py
endplay/dealer/generate.py
endplay/dealer/runscript.py
endplay/evaluate/__init__.py
endplay/experimental/__init__.py
endplay/experimental/playdetect.py
endplay/interact/__init__.py
endplay/interact/__main__.py
endplay/interact/actions.py
endplay/interact/commandobject.py
endplay/interact/frontends/__init__.py
endplay/interact/frontends/base.py
endplay/interact/frontends/cmd.py
endplay/interact/frontends/curses.py
endplay/interact/frontends/html/__init__.py
endplay/interact/frontends/html/index.html
endplay/interact/frontends/html/script.js
endplay/interact/frontends/html/style.css
endplay/parsers/__init__.py
endplay/parsers/dealer.py
endplay/parsers/json.py
endplay/parsers/lin.py
endplay/parsers/pbn.py
endplay/py.typed
endplay/stats/__init__.py
endplay/types/__init__.py
endplay/types/bid.py
endplay/types/board.py
endplay/types/card.py
endplay/types/contract.py
endplay/types/deal.py
endplay/types/denom.py
endplay/types/hand.py
endplay/types/penalty.py
endplay/types/player.py
endplay/types/rank.py
endplay/types/suitholding.py
endplay/types/vul.py
endplay/utils/__init__.py
endplay/utils/escape.py
endplay/utils/io.py
endplay/utils/play.py
endplay/_dds/__init__.py
endplay/_dds/dds.dll
endplay-0.5.11.dist-info/entry_points.txt
endplay-0.5.11.dist-info/LICENCE
endplay-0.5.11.dist-info/METADATA
endplay-0.5.11.dist-info/WHEEL
endplay-0.5.11.dist-info/RECORD
