Metadata-Version: 2.1
Name: endplay
Version: 0.5.11
Summary: A suite of tools for generation and analysis of bridge deals
License: MIT
Keywords: bridge,cards,games,double dummy,dds,analysis,stats,deal,dealer
Author: Dominic Price
Author-email: dominicprice@outlook.com
Requires-Python: >=3.9,<4.0
Classifier: Development Status :: 4 - Beta
Classifier: License :: OSI Approved :: MIT License
Classifier: Natural Language :: English
Classifier: Operating System :: OS Independent
Classifier: Programming Language :: Python :: 3
Classifier: Programming Language :: Python :: 3.9
Classifier: Programming Language :: Python :: 3.10
Classifier: Programming Language :: Python :: 3.11
Classifier: Programming Language :: Python :: 3.12
Classifier: Programming Language :: Python :: 3.13
Classifier: Topic :: Games/Entertainment
Requires-Dist: matplotlib (>=3.0)
Requires-Dist: more-itertools (>=9.0)
Requires-Dist: numpy (>=1.26)
Requires-Dist: pyparsing (>=3.0)
Requires-Dist: tqdm (>=4.65)
Project-URL: Bug Tracker, https://github.com/dominicprice/endplay/issues
Project-URL: Documentation, https://endplay.readthedocs.io
Project-URL: Homepage, https://github.com/dominicprice/endplay
